alice_open_source_package-1.0.dist-info/DESCRIPTION.rst
alice_open_source_package-1.0.dist-info/METADATA
alice_open_source_package-1.0.dist-info/RECORD
alice_open_source_package-1.0.dist-info/WHEEL
alice_open_source_package-1.0.dist-info/metadata.json
alice_open_source_package-1.0.dist-info/top_level.txt
alice_package/__init__.py
foo_package/__init__.py
