Metadata-Version: 2.0
Name: alice-open-source-package
Version: 1.0
Summary: Alice open source package
Home-page: UNKNOWN
Author: Alice
Author-email: srossross@gmail.com
License: BSD
Platform: UNKNOWN
Requires-Dist: certifi
